README.md
setup.cfg
setup.py
aws_prometheus_exporter/__init__.py
aws_prometheus_exporter/__main__.py
aws_prometheus_exporter.egg-info/PKG-INFO
aws_prometheus_exporter.egg-info/SOURCES.txt
aws_prometheus_exporter.egg-info/dependency_links.txt
aws_prometheus_exporter.egg-info/requires.txt
aws_prometheus_exporter.egg-info/top_level.txt