Metadata-Version: 1.2
Name: aws-prometheus-exporter
Version: 0.1.2
Summary: AWS exporter for Prometheus
Home-page: https://github.com/movio/aws-prometheus-exporter
Author: Movio Developers
Author-email: nicolas@movio.co
License: MIT
Keywords: aws monitoring prometheus
Platform: UNKNOWN
Classifier: Development Status :: 3 - Alpha
Classifier: Intended Audience :: Developers
Classifier: Intended Audience :: Information Technology
Classifier: Intended Audience :: System Administrators
Classifier: Programming Language :: Python :: 3
Classifier: Programming Language :: Python :: 3.7
Classifier: Topic :: System :: Monitoring
Classifier: License :: OSI Approved :: Apache Software License
Requires-Python: >=3.7
